[
  {
    "id": "6287891540792-1601469859@g.us",
    "key": "FF",
    "response": " -ˏˋ⋆ 𝐅𝐫𝐞𝐞 𝐅𝐢𝐫𝐞 ⋆ˊˎ- \n \n𝑺𝒕𝒂𝒕𝒖𝒔 : 𝑹𝒆𝒂𝒅𝒚 ✅\n\n𝟻𝟶 💎 𝟽.𝟻𝟶𝟶\n𝟽𝟶 💎 𝟿.𝟻𝟶𝟶\n𝟷𝟺𝟶 💎 𝟷𝟾.𝟻𝟶𝟶\n𝟹𝟻𝟻 💎 𝟺𝟼.𝟶𝟶𝟶\n𝟽𝟸𝟶 💎 𝟿𝟷.𝟶𝟶𝟶\n𝟷.𝟺𝟻𝟶 💎 𝟷𝟾𝟻.𝟶𝟶𝟶\n𝟸.𝟷𝟾𝟶 💎 𝟸𝟾𝟶.𝟶𝟶𝟶\n𝟹.𝟼𝟺𝟶 💎 𝟺𝟼𝟻.𝟶𝟶𝟶\n𝟽.𝟸𝟿𝟶 💎 𝟿𝟹𝟻.𝟶𝟶𝟶\n\n˚𐙚 ᴍᴇᴍʙᴇʀ ᴍɪɴɢɢᴜᴀɴ 𝟸𝟾.𝟻𝟶𝟶\n˚𐙚 ᴍᴇᴍʙᴇʀ ʙᴜʟᴀɴᴀɴ 𝟾𝟻.𝟻𝟶𝟶\n\n✤ via id\n✤ proses 1-15 menit\n tergantung antrian\n\n‿︵‿︵୨˚̣̣̣͙୧ - -୨˚̣̣̣͙୧‿︵‿︵",
    "isImage": false,
    "image_url": "-"
  },
  {
    "id": "6287891540792-1601469859@g.us",
    "key": "Genshin",
    "response": " -ˏˋ⋆ 𝐆𝐞𝐧𝐬𝐡𝐢𝐧 𝐈𝐦𝐩𝐚𝐜𝐭 ⋆ˊˎ- \n \n 𝑺𝒕𝒂𝒕𝒖𝒔 : 𝑹𝒆𝒂𝒅𝒚 ✅\n\n𝟼𝟶 ✧ 𝟷𝟷.𝟻𝟶𝟶\n𝟹𝟶𝟶 + 𝟹𝟶 ✧ 𝟻𝟾.𝟶𝟶𝟶\n𝟿𝟾𝟶 + 𝟷𝟷𝟶 ✧ 𝟷𝟽𝟺.𝟶𝟶𝟶\n𝟷.𝟿𝟾𝟶 + 𝟸𝟼𝟶 ✧ 𝟹𝟽𝟾.𝟶𝟶𝟶\n𝟹.𝟸𝟾𝟶 + 𝟼𝟶𝟶 ✧ 𝟻𝟾𝟹.𝟶𝟶𝟶\n𝟼.𝟺𝟾𝟶 + 𝟷.𝟼𝟶𝟶 ✧ 𝟷.𝟷𝟼𝟻.𝟶𝟶𝟶\n\nᯓᡣ𐭩 ʙʟᴇssɪɴɢ ᴏғ ᴛʜᴇ ᴡᴇʟᴋɪɴ ᴍᴏᴏɴ = 𝟻𝟾.𝟶𝟶𝟶\n\n✤ via id\n✤ proses 1-15 menit\n tergantung antrian\n\n‿︵‿︵୨˚̣̣̣͙୧ - -୨˚̣̣̣͙୧‿︵‿︵",
    "isImage": false,
    "image_url": "-"
  },
  {
    "id": "6287891540792-1601469859@g.us",
    "key": "HOK",
    "response": " -ˏˋ⋆ 𝐇𝐨𝐧𝐨𝐫 𝐎𝐟 𝐊𝐢𝐧𝐠 ⋆ˊˎ- \n \n𝑺𝒕𝒂𝒕𝒖𝒔 : 𝑹𝒆𝒂𝒅𝒚 ✅\n\n𝟾𝟶 + 𝟾 🎟️ 𝟷𝟹.𝟻𝟶𝟶\n𝟸𝟺𝟶 + 𝟷𝟽 🎟️ 𝟺𝟶.𝟻𝟶𝟶\n𝟺𝟶𝟶 + 𝟹𝟸 🎟️ 𝟼𝟾.𝟻𝟶𝟶\n𝟻𝟼𝟶 + 𝟺𝟻 🎟️ 𝟿𝟺.𝟶𝟶𝟶\n𝟾𝟶𝟶 + 𝟿𝟻 🎟️ 𝟷𝟹𝟾.𝟶𝟶𝟶\n𝟷.𝟸𝟶𝟶 + 𝟷𝟻𝟹 🎟️ 𝟸𝟶𝟸.𝟻𝟶𝟶\n𝟸.𝟺𝟶𝟶 + 𝟹𝟸𝟺 🎟️ 𝟺𝟷𝟺.𝟶𝟶𝟶\n𝟺.𝟶𝟶𝟶 + 𝟻𝟾𝟶 🎟️ 𝟼𝟿𝟶.𝟶𝟶𝟶\n𝟾𝟶𝟶𝟶 + 𝟷.𝟷𝟼𝟶 🎟️ 𝟷.𝟹𝟾𝟻.𝟶𝟶𝟶\n\n✤ via id\n✤ proses 1-15 menit\n tergantung antrian\n\n‿︵‿︵୨˚̣̣̣͙୧ - -୨˚̣̣̣͙୧‿︵‿︵",
    "isImage": false,
    "image_url": "-"
  },
  {
    "id": "6287891540792-1601469859@g.us",
    "key": "Joki",
    "response": " -ˏˋ⋆ 𝐉𝐨𝐤𝐢 ⋆ˊˎ- \n\n𝑺𝒕𝒂𝒕𝒖𝒔 : 𝑹𝒆𝒂𝒅𝒚 ✅\n\n✿﹒𝐄ρ𝗂𝖼 : 𝟽.𝟶𝟶𝟶 / ★\n✿﹒𝐋𝖾𝗀𝖾𐓣ᑯ : 𝟾.𝟶𝟶𝟶 / ★\n✿﹒𝐌𝗒𝗍ɦ𝗂𝖼 : 𝟷𝟷.𝟶𝟶𝟶 / ★\n✿﹒𝐇ⱺ𐓣ⱺ𝗋 : 𝟷𝟺.𝟶𝟶𝟶 / ★\n✿﹒𝐆ᥣⱺ𝗋𝗒 : 𝟷𝟽.𝟶𝟶𝟶 / ★\n✿﹒𝚰ꭑꭑⱺ𝗋𝗍αᥣ : 𝟸𝟷.𝟶𝟶𝟶 / ★\n\n✿﹒ 𝐂ᥣα𝗌𝗌𝗂𝖼 : 𝟾.𝟶𝟶𝟶 / win\n\n⋆𐙚 bukan room wangi/dukun\n⋆𐙚 matikan v2l\n⋆𐙚 data 1000% aman\n⋆𐙚 selama proses dilarang login\n⋆𐙚 req hero \n⋆𐙚 order banyak dapat diskon\n\n‿︵‿︵୨˚̣̣̣͙୧ - -୨˚̣̣̣͙୧‿︵‿︵",
    "isImage": false,
    "image_url": "-"
  },
  {
    "id": "6287891540792-1601469859@g.us",
    "key": "ML A",
    "response": " -ˏˋ⋆ 𝐌𝐋 𝐀 ⋆ˊˎ- \n \n 𝑺𝒕𝒂𝒕𝒖𝒔 : 𝑹𝒆𝒂𝒅𝒚 ✅\n\n𝟷𝟸💎 𝟹.𝟻𝟶𝟶\n𝟷𝟿💎 𝟻.𝟻𝟶𝟶\n𝟸𝟾💎 𝟽.𝟾𝟶𝟶\n𝟺𝟺💎 𝟷𝟷.𝟻𝟶𝟶\n𝟻𝟿💎 𝟷𝟻.𝟶𝟶𝟶\n\n✤ via id\n✤ proses 1-15 menit\n tergantung antrian\n\n‿︵‿︵୨˚̣̣̣͙୧ - -୨˚̣̣̣͙୧‿︵‿︵",
    "isImage": false,
    "image_url": "-"
  },
  {
    "id": "6287891540792-1601469859@g.us",
    "key": "ML B",
    "response": " -ˏˋ⋆ 𝐌𝐋 𝐁 ⋆ˊˎ- \n \n 𝑺𝒕𝒂𝒕𝒖𝒔 : 𝑹𝒆𝒂𝒅𝒚 ✅\n\n𝟾𝟻 💎 𝟸𝟷.𝟻𝟶𝟶\n𝟷𝟽𝟶 💎 𝟺𝟹.𝟶𝟶𝟶\n𝟸𝟺𝟶 💎 𝟼𝟷.𝟶𝟶𝟶\n𝟸𝟾𝟺 💎 𝟽𝟷.𝟶𝟶𝟶\n𝟸𝟿𝟼 💎 𝟽𝟺.𝟻𝟶𝟶\n𝟹𝟶𝟷 💎 𝟽𝟼.𝟶𝟶𝟶\n𝟺𝟶𝟾 💎 𝟷𝟶𝟺.𝟶𝟶𝟶\n𝟺𝟻𝟸 💎 𝟷𝟷𝟼.𝟶𝟶𝟶\n𝟻𝟷𝟸 💎 𝟷𝟹𝟶.𝟶𝟶𝟶\n𝟻𝟼𝟾 💎 𝟷𝟺𝟸.𝟶𝟶𝟶\n𝟼𝟷𝟸 💎 𝟷𝟻𝟸.𝟶𝟶𝟶\n𝟼𝟻𝟹 💎 𝟷𝟼𝟸.𝟶𝟶𝟶\n𝟽𝟶𝟺 💎 𝟷𝟽𝟾.𝟶𝟶𝟶\n𝟽𝟹𝟾 💎 𝟷𝟾𝟻.𝟶𝟶𝟶\n𝟽𝟾𝟸 💎 𝟷𝟿𝟻.𝟶𝟶𝟶\n𝟾𝟶𝟾 💎 𝟸𝟶𝟷.𝟶𝟶𝟶\n𝟾𝟻𝟸 💎 𝟸𝟷𝟻.𝟶𝟶𝟶\n𝟾𝟽𝟻 💎 𝟸𝟷𝟸.𝟶𝟶𝟶\n𝟿𝟶𝟾 💎 𝟸𝟹𝟶.𝟶𝟶𝟶\n𝟿𝟼𝟶 💎 𝟸𝟹𝟼.𝟶𝟶𝟶\n𝟷.𝟶𝟺𝟻💎 𝟸𝟻𝟽.𝟶𝟶𝟶\n\n✤ via id\n✤ proses 1-15 menit\n tergantung antrian\n\n‿︵‿︵୨˚̣̣̣͙୧ - -୨˚̣̣̣͙୧‿︵‿︵",
    "isImage": false,
    "image_url": "-"
  },
  {
    "id": "6287891540792-1601469859@g.us",
    "key": "ML C",
    "response": " -ˏˋ⋆ 𝐌𝐋 𝐂 ⋆ˊˎ- \n \n 𝑺𝒕𝒂𝒕𝒖𝒔 : 𝑹𝒆𝒂𝒅𝒚 ✅\n \n𝟷.𝟷𝟷𝟻 💎 𝟸𝟽𝟹.𝟶𝟶𝟶\n𝟷.𝟸𝟾𝟹 💎 𝟹𝟷𝟻.𝟶𝟶𝟶\n𝟷𝟺𝟺𝟹 💎 𝟹𝟻𝟺.𝟶𝟶𝟶\n𝟷.𝟽𝟻𝟶 💎 𝟺𝟸𝟹.𝟶𝟶𝟶\n𝟸.𝟶𝟷𝟶 💎 𝟺𝟼𝟻.𝟶𝟶𝟶\n𝟸.𝟸𝟻𝟶 💎 𝟻𝟸𝟶.𝟶𝟶𝟶\n𝟸.𝟺𝟷𝟾 💎 𝟻𝟽𝟶.𝟶𝟶𝟶\n𝟸.𝟾𝟾𝟻 💎 𝟼𝟽𝟽.𝟶𝟶𝟶\n𝟹.𝟷𝟸𝟻 💎 𝟽𝟻𝟶.𝟶𝟶𝟶\n𝟹.𝟺𝟻𝟻 💎 𝟾𝟹𝟶.𝟶𝟶𝟶\n𝟹.𝟽𝟼𝟶 💎 𝟾𝟿𝟻.𝟶𝟶𝟶\n𝟺.𝟷𝟶𝟻 💎 𝟿𝟻𝟽.𝟶𝟶𝟶\n𝟺.𝟺𝟸𝟾 💎 𝟷.𝟶𝟺𝟻.𝟶𝟶𝟶\n𝟺.𝟾𝟹𝟶 💎 𝟷.𝟷𝟸𝟶.𝟶𝟶𝟶\n𝟻.𝟶𝟶𝟶 💎 𝟷.𝟷𝟽𝟶.𝟶𝟶𝟶\n\n✤ via id\n✤ proses 1-15 menit\n tergantung antrian\n\n‿︵‿︵୨˚̣̣̣͙୧ - -୨˚̣̣̣͙୧‿︵‿︵",
    "isImage": false,
    "image_url": "-"
  },
  {
    "id": "6287891540792-1601469859@g.us",
    "key": "ML Vilog",
    "response": " -ˏˋ⋆ 𝐌𝐋 𝐕𝐢𝐥𝐨𝐠 ⋆ˊˎ- \n \n𝑺𝒕𝒂𝒕𝒖𝒔 : 𝑹𝒆𝒂𝒅𝒚 ✅\n\n𝟻𝟼𝟻 💎 𝟷𝟸𝟻.𝟶𝟶𝟶\n𝟷.𝟷𝟻𝟻 💎 𝟸𝟻𝟶.𝟶𝟶𝟶\n𝟷.𝟽𝟼𝟻 💎 𝟹𝟽𝟹.𝟶𝟶𝟶\n𝟸.𝟿𝟽𝟻 💎 𝟻𝟾𝟻.𝟶𝟶𝟶\n\n𝚆𝙳𝙿 𝟸𝟹.𝟻𝟶𝟶\n𝚃𝚠𝚒𝚕𝚒𝚐𝚑𝚝 𝟷𝟸𝟻.𝟶𝟶𝟶\n\n\n✤ via login akun buyer\n✤ aman 1000% ada invoice\n (bukti topup)\n✤ dimainkan 3-5 match\n✤ proses 45 menit - 2 jam\n✤ pembelian wdp harus\n di sertakan nominal lain\n misal : wdp + 565 dm\n \n‿︵‿︵୨˚̣̣̣͙୧ - -୨˚̣̣̣͙୧‿︵‿︵",
    "isImage": false,
    "image_url": "-"
  },
  {
    "id": "6287891540792-1601469859@g.us",
    "key": "Starlight",
    "response": "-ˏˋ⋆ 𝐒𝐭𝐚𝐫𝐥𝐢𝐠𝐡𝐭 ⋆ˊˎ- \n\n𝙑𝙞𝙖 𝙄𝘿 ✅\n𝟹𝟶𝟶 💎 𝟽𝟻.𝟶𝟶𝟶\n𝟽𝟻𝟶 💎 𝟷𝟽𝟼.𝟶𝟶𝟶\n\n𝙑𝙞𝙖 𝙜𝙞𝙛𝙩 ✅\n𝟹𝟶𝟶💎 𝟹𝟼.𝟶𝟶𝟶\n𝟽𝟻𝟶💎 𝟿𝟶.𝟶𝟶𝟶\n\n\n⚝──⭒─⭑─⭒──⚝\n★ 𝚟𝚒𝚊 𝚒𝚍 𝚕𝚊𝚗𝚐𝚜𝚞𝚗𝚐 𝚖𝚊𝚜𝚞𝚔\n★ 𝚟𝚒𝚊 𝚒𝚍 𝚍𝚒 𝚒𝚜𝚒 𝚍𝚒𝚊𝚖𝚘𝚗𝚍\n★ 𝚟𝚒𝚊 𝚐𝚒𝚏𝚝 𝚍𝚎𝚕𝚊𝚢 𝟽-𝟾 𝚑𝚊𝚛𝚒\n 𝚋𝚎𝚛𝚝𝚎𝚖𝚊𝚗 𝚍𝚎𝚗𝚐𝚊𝚗 𝚊𝚔𝚞𝚗 𝚐𝚒𝚏𝚝 𝚍𝚊𝚑𝚞𝚕𝚞\n★ 𝚍𝚒𝚙𝚛𝚘𝚜𝚎𝚜 𝚜𝚎𝚜𝚞𝚊𝚒 𝚊𝚗𝚝𝚛𝚒𝚊𝚗\n★ 𝚗𝚘 𝚐𝚊𝚗𝚝𝚒 𝚗𝚒𝚌𝚔𝚗𝚊𝚖𝚎 ✘\n\n‿︵‿︵୨˚̣̣̣͙୧ - -୨˚̣̣̣͙୧‿︵‿︵",
    "isImage": false,
    "image_url": "-"
  },
  {
    "id": "6287891540792-1601469859@g.us",
    "key": "PUBG",
    "response": " -ˏˋ⋆ 𝐏𝐔𝐁𝐆 ⋆ˊˎ- \n \n𝑺𝒕𝒂𝒕𝒖𝒔 : 𝑹𝒆𝒂𝒅𝒚 ✅\n\n𝟹𝟶 🔰 𝟼.𝟷𝟶𝟶\n𝟼𝟶 🔰 𝟷𝟸.𝟻𝟶𝟶\n𝟹𝟸𝟻 🔰 𝟼𝟶.𝟶𝟶𝟶\n𝟼𝟼𝟶 🔰 𝟷𝟸𝟷.𝟶𝟶𝟶\n𝟷.𝟾𝟶𝟶 🔰 𝟹𝟶𝟸.𝟻𝟶𝟶\n𝟹.𝟾𝟻𝟶 🔰 𝟼𝟶𝟾.𝟶𝟶𝟶\n𝟾.𝟷𝟶𝟶 🔰 𝟷.𝟸𝟷𝟻.𝟶𝟶𝟶\n\n✮ ʀᴘ 𝟷𝟺𝟼.𝟻𝟶𝟶\n✮ ᴇʟɪᴛᴇ 𝟹𝟽𝟷.𝟶𝟶𝟶\n\n✤ region indo\n✤ via id\n✤ proses 1-15 menit\n tergantung antrian\n\n‿︵‿︵୨˚̣̣̣͙୧ - -୨˚̣̣̣͙୧‿︵‿︵",
    "isImage": false,
    "image_url": "-"
  },
  {
    "id": "6287891540792-1601469859@g.us",
    "key": "WDP",
    "response": "-ˏˋ⋆ 𝐖𝐃𝐏 ⋆ˊˎ- \n\n𝑺𝒕𝒂𝒕𝒖𝒔 : 𝑹𝒆𝒂𝒅𝒚 ✅\n\n𝐖𝐃𝐏 𝐈𝐧𝐝𝐨 : 26.000\n𝐖𝐃𝐏 𝐓𝐮𝐫𝐤𝐲 : 20.000\n\nꕤ 𝗄ᥣα𝗂ꭑ ɦα𝗋𝗂α𐓣 20, 𝗌𝖾ᥣαꭑα 7 ɦα𝗋𝗂\nꕤ 𝗄ᥣα𝗂ꭑ ᥣα𐓣𝗀𝗌υ𐓣𝗀 80\n\n. ⋅ ˚̣- : ✧ : – ⭒ ⊹ ⭒ – : ✧ : -˚̣⋅ .\n\n✦ 1 ωᑯρ = 7 ɦα𝗋𝗂\n✦ ωᑯρ ᑯαρα𝗍 ᑯ𝗂𝗍υꭑρυ𝗄 ɦ𝗂𐓣𝗀𝗀α 10\n✦ 𝗍𝖾𝗋ɦ𝗂𝗍υ𐓣𝗀 ꭑ𝗂𝗌𝗂 𝗍ⱺρυρ 100 ᑯꭑ\n\n‿︵‿︵ʚ˚̣̣̣͙ɞ・❉・ ʚ˚̣̣̣͙ɞ‿︵‿︵",
    "isImage": false,
    "image_url": "-"
  },
  {
    "id": "6287891540792-1601469859@g.us",
    "key": "Format Oorder",
    "response": "❀ *Format Order* ❀\n\n༻❁༺ ─── ⋆⋅☆⋅⋆ ── ༻❁༺\n✮ 𐓣𝗂𝖼𝗄 :\n✮ 𝗂ᑯ & 𝗌𝖾𝗋𝗏𝖾𝗋 :\n✮ ⱺ𝗋ᑯ𝖾𝗋 :\n\nⲛⲟⲧⲉ :\nkᥱsᥲᥣᥲһᥲᥒ іძ/sᥱr᥎ᥱr ᑲᥙkᥲᥒ 𝗍ᥲᥒggᥙᥒg ȷᥲᥕᥲᑲ kᥲmі\n⍴ᥲs𝗍іkᥲᥒ іძ/sᥱr᥎ᥱr ᑲᥱᥒᥲr\n༻❁༺ ─── ⋆⋅☆⋅⋆ ── ༻❁༺",
    "isImage": false,
    "image_url": "-"
  },
  {
    "id": "6287891540792-1601469859@g.us",
    "key": "Format Vilog",
    "response": "✤ 𝐅𝐨𝐫𝐦𝐚𝐭 𝐕𝐢𝐥𝐨𝐠 ✤\n\n༻❁༺ ─── ⋆⋅☆⋅⋆ ── ༻❁༺\nᥣⱺ𝗀 :\n𝖾ꭑα𝗂ᥣ :\nρα𝗌𝗌ωⱺ𝗋ᑯ :\n\n𝑵𝒐𝒕𝒆 :\n❖ ⍴ᥲs𝗍іkᥲᥒ ᥱmᥲіᥣ/⍴ᥕ ᑲᥱᥒᥲr\n❖ ȷᥲᥒgᥲᥒ ᥣ᥆gіᥒ sᥱᥣᥲmᥲ ⍴r᥆sᥱs \n ᑲᥱrᥣᥲᥒgsᥙᥒg\n\n༻❁༺ ─── ⋆⋅☆⋅⋆ ── ༻❁༺",
    "isImage": false,
    "image_url": "-"
  },
  {
    "id": "6287891540792-1601469859@g.us",
    "key": "Payment",
    "response": "ʚ ︵‿︵‿︵꒰ 𝑷𝒂𝒚𝒎𝒆𝒏𝒕 ꒱︵‿︵‿︵ ɞ\n┊﹍﹍﹍﹍﹍﹍﹍﹍﹍﹍﹍﹍﹍﹍┊\n꒰ 💭 ꒱ 𝐃𝐚𝐧𝐚 \n┊. 085888362486\n┊. 𝖠𝗋ꪱᜒ𐓣ᑯɑ 𝖭υ𝗋 𝖠𐓣𝗀𝗀ꪱᜒ𝗍ɑ 𝖥ꪱᜒ𝗍𝗋ꪱᜒ \n꒰ 💭 ꒱ 𝐆𝐨𝐩𝐚𝐲\n┊. 087891540792\n┊. 𝖠𐓣𝗀𝗀ꪱᜒ𝗍ɑ\n꒰ 💭 ꒱ 𝐒𝐡𝐨𝐩𝐞𝐞𝐏𝐚𝐲\n┊. 085888362486\n┊. 𝖠𐓣𝗀𝗀ꪱᜒ𝗍ɑ_𝖠𝗋ꪱᜒ𐓣ᑯɑ \n꒰ 💭 ꒱ 𝐒𝐞𝐚𝐁𝐚𝐧𝐤\n┊. 901752694509\n┊. 𝖠𝗋ꪱᜒ𐓣ᑯɑ 𝖭υ𝗋 𝖠𐓣𝗀𝗀ꪱᜒ𝗍ɑ 𝖥ꪱᜒ𝗍𝗋ꪱᜒ\n꒰ 💭 ꒱ 𝐁𝐒𝐈\n┊. 1041172173 \n┊. 𝖠𝗋ꪱᜒ𐓣ᑯɑ 𝖭υ𝗋 𝖠𐓣𝗀𝗀ꪱᜒ𝗍ɑ 𝖥ꪱᜒ𝗍𝗋ꪱᜒ\n꒰ 💭 ꒱ 𝐐𝐫𝐢𝐬, 𝐀𝐥𝐟𝐚𝐦𝐚𝐫𝐭, 𝐈𝐧𝐝𝐨𝐦𝐚𝐫𝐭\n┊. 𝐒𝗂ᥣαɦ𝗄α𐓣 ꭑ𝗂𐓣𝗍α 𝐀ᑯꭑ𝗂𐓣\n꒰ 💭 ꒱ 𝐓𝐅 𝐁𝐞𝐝𝐚 𝐁𝐚𝐧𝐤\n┊. 𝐒𝗂ᥣαɦ𝗄α𐓣 ꭑ𝗂𐓣𝗍α 𝐀ᑯꭑ𝗂𐓣\n﹍﹍﹍﹍﹍﹍﹍﹍﹍﹍﹍﹍﹍﹍﹍\n ︶︶︶︶︶︶︶︶︶︶︶︶\nᯓ★ ʙᴀɴᴋ -> ᴅᴀɴᴀ +𝟻𝟶𝟶\nᯓ★ ᴛғ ʜᴀɴʏᴀ ᴋᴇ ɴᴏᴍᴏʀ ᴅɪᴀᴛᴀs\nᯓ★ ᴊɪᴋᴀ ᴀᴅᴀ ʏᴀɴɢ ᴋᴜʀᴀɴɢ ᴊᴇʟᴀs\n sɪʟᴀʜᴋᴀɴ ᴄʜᴀᴛ ᴀᴅᴍɪɴ\nᯓ★ ᴋɪʀɪᴍ ʙᴜᴋᴛɪ ᴛғ, ᴀᴅᴍɪɴ ᴄᴇᴋ\n ᴘʀᴏsᴇs",
    "isImage": false,
    "image_url": "-"
  },
  {
    "id": "6287891540792-1601469859@g.us",
    "key": "Promo",
    "response": " -ˏˋ⋆ 𝐏𝐫𝐨𝐦𝐨 ⋆ˊˎ- \n\n✶ 𝑴𝑳𝑩𝑩 ✶\n𝘞𝘋𝘗 : 25.500\n\n𝟸𝟾𝟺 💎 𝟽𝟶.𝟶𝟶𝟶\n𝟹𝟶𝟷 💎 𝟽𝟻.𝟶𝟶𝟶\n𝟷.𝟶𝟺𝟻 💎 𝟸𝟻𝟶.𝟶𝟶𝟶\n𝟸.𝟶𝟷𝟶 💎 𝟺𝟻𝟶.𝟶𝟶𝟶\n𝟹.𝟹𝟶𝟻 💎 𝟽𝟹𝟻.𝟶𝟶𝟶\n𝟺.𝟺𝟸𝟾 💎 𝟿𝟼𝟸.𝟶𝟶𝟶\n𝟼.𝟾𝟹𝟶 💎 𝟷.𝟻𝟻𝟸.𝟶𝟶𝟶\n\n✤ via id\n✤ proses 5-15 menit\n tergantung antrian\n✤ order = sabar\n\n‿︵‿︵୨˚̣̣̣͙୧ - -୨˚̣̣̣͙୧‿︵‿︵",
    "isImage": false,
    "image_url": "-"
  },
  {
    "id": "6287891540792-1601469859@g.us",
    "key": "Tips Hemat Collector",
    "response": "Tips Hemat Collector",
    "isImage": true,
    "image_url": "https://telegra.ph/file/d5a5ef6de0581e44e1d8c.jpg"
  },
  {
    "id": "6287891540792-1601469859@g.us",
    "key": "SQ Verif",
    "response": " -ˏˋ⋆ 𝐒𝐪𝐮𝐚𝐝 𝐕𝐞𝐫𝐢𝐟𝐞𝐝 ⋆ˊˎ-\n \n✅ #𝟏 ( Nevermind )\n✅ 𝑶𝒏𝒊𝒄 ( Onic Esport )\n \nꕤ﹒ 𝟻 𝙷𝚊𝚛𝚒 : 𝟸𝟾.𝟻𝟶𝟶\nꕤ﹒ 𝟽 𝙷𝚊𝚛𝚒 : 𝟹𝟻.𝟶𝟶𝟶\nꕤ﹒ 𝟷𝟶 𝙷𝚊𝚛𝚒 : 𝟻𝟷.𝟶𝟶𝟶\nꕤ﹒ 𝟷𝟻 𝙷𝚊𝚛𝚒 : 𝟼𝟼.𝟶𝟶𝟶\nꕤ﹒ 𝟹𝟶 𝙷𝚊𝚛𝚒 : 𝟷𝟶𝟶.𝟶𝟶𝟶\nꕤ﹒ 𝟼𝟶 𝙷𝚊𝚛𝚒 : 𝟷𝟾𝟹.𝟶𝟶𝟶\n\n✿﹒Langsung masuk grup\n✿﹒Keluar squad/Ganti akun\ntidak bisa masuk lagi ✗\n\n‿︵‿︵୨˚̣̣̣͙୧ - -୨˚̣̣̣͙୧‿︵‿︵",
    "isImage": false,
    "image_url": "-"
  },
  {
    "id": "6287891540792-1601469859@g.us",
    "key": "RoomTour",
    "response": "-ˏˋ⋆ 𝐑𝐨𝐨𝐦𝐓𝐨𝐮𝐫 ⋆ˊˎ- \n\n✮ 𝑷𝒓𝒊𝒗𝒂𝒕𝒆 ( 𝟓 𝒗𝒔 𝟓 )\n➔﹒𝟎𝟕.𝟎𝟎 - 𝟏𝟗.𝟎𝟎 𝑾𝑰𝑩\n𝟷 ᴍᴀᴛᴄʜ : 𝟸𝟶.𝟶𝟶𝟶\n𝟷 ᴊᴀᴍ : 𝟸𝟶.𝟶𝟶𝟶\n\n➔﹒𝟐𝟎.𝟎𝟎 - 𝟎𝟐.𝟎𝟎 𝑾𝑰𝑩\n𝟷 ᴍᴀᴛᴄʜ : 𝟸𝟶.𝟶𝟶𝟶\n𝟷 ᴊᴀᴍ : 𝟹𝟻.𝟶𝟶𝟶\n\n﹒✸﹒𝑩𝒖𝒚 𝟏 𝑮𝒆𝒕 𝟏 𝑴𝒂𝒕𝒄𝒉\n𝑩𝒆𝒓𝒍𝒂𝒌𝒖 𝑯𝒂𝒓𝒊 𝑺𝒆𝒏𝒊𝒏 - 𝑱𝒖𝒎𝒂𝒕\n𝑲𝒉𝒖𝒔𝒖𝒔 𝒋𝒂𝒎 𝟎𝟖.𝟎𝟎 - 𝟏𝟖.𝟎𝟎 ﹒✸﹒\n\n\n✧ Benefit RoomTour\n▣﹒𝘈𝘭𝘭 𝘴𝘬𝘪𝘯 & 𝘏𝘦𝘳𝘰 𝘜𝘯𝘭𝘰𝘤𝘬𝘦𝘥\n▣﹒𝘌𝘮𝘣𝘭𝘦𝘮 𝘈𝘭𝘭 𝘔𝘢𝘹\n▣﹒𝘒𝘢𝘮𝘦𝘳𝘢 3𝘋 𝘝𝘪𝘦𝘸\n▣﹒𝘋𝘳𝘢𝘧𝘵 𝘣𝘢𝘯 10\n▣﹒𝘏𝘪𝘴𝘵𝘰𝘳𝘺 𝘵𝘦𝘳𝘵𝘶𝘭𝘪𝘴 𝘛𝘶𝘳𝘯𝘢𝘮𝘦𝘯\n\n✧ 𝑵𝑶𝑻𝑬\n▣﹒𝘛𝘪𝘥𝘢𝘬 𝘣𝘪𝘴𝘢 𝘮𝘦𝘯𝘨𝘶𝘣𝘢𝘩 𝘫𝘢𝘥𝘸𝘢𝘭\n▣﹒1 𝘮𝘢𝘵𝘤𝘩 ▶ 30 𝘮𝘦𝘯𝘪𝘵\n▣﹒𝘙𝘦𝘧𝘧𝘶𝘯𝘥 = 𝘏𝘢𝘯𝘨𝘶𝘴\n\n‿︵‿︵୨˚̣̣̣͙୧ - -୨˚̣̣̣͙୧‿︵‿︵",
    "isImage": false,
    "image_url": "-"
  },
  {
    "id": "6287891540792-1601469859@g.us",
    "key": "Am prem",
    "response": " -ˏˋ⋆ 𝐀𝐥𝐥𝐢𝐠𝐡𝐭 𝐌𝐨𝐭𝐢𝐨𝐧 𝐏𝐫𝐢𝐯𝐚𝐭𝐞 ⋆ˊˎ-\n\n❀. tidak full 1 thn\n╰⪼ 𝟐.𝟎𝟎𝟎\n\nꕤ﹒ ᴇᴍᴀɪʟ ᴅᴀʀɪ sᴇʟʟᴇʀ +𝟸𝟶𝟶𝟶\nꕤ﹒ ᴡᴀᴊɪʙ ᴇᴍᴀɪʟ ғʀᴇsʜ\nꕤ﹒ ᴘʀᴏsᴇs 𝟷𝟶-𝟹𝟶 ᴍᴇɴɪᴛ, ᴍᴀx 𝟸𝟺 ᴊᴀᴍ\nꕤ﹒ ᴏʀᴅᴇʀ = sᴀʙᴀʀ\n\n‿︵‿︵୨˚̣̣̣͙୧ - -୨˚̣̣̣͙୧‿︵‿︵",
    "isImage": false,
    "image_url": "-"
  },
  {
    "id": "6287891540792-1601469859@g.us",
    "key": "Format Order AM",
    "response": "❀ 𝐅𝐨𝐫𝐦𝐚𝐭 𝐎𝐫𝐝𝐞𝐫 𝐀𝐌 ❀\n\n༻❁༺ ─── ⋆⋅☆⋅⋆ ── ༻❁༺\n✦﹒ᴛᴀɴɢɢᴀʟ ᴏʀᴅᴇʀ :\n✦﹒ᴇᴍᴀɪʟ :\n✦﹒ᴘᴀssᴡᴏʀᴅ : \n\n.✶﹒Isi dengan benar .✶﹒\n༻❁༺ ─── ⋆⋅☆⋅⋆ ── ༻❁༺",
    "isImage": false,
    "image_url": "-"
  },
  {
    "id": "6287891540792-1601469859@g.us",
    "key": "Gift Skin",
    "response": " -ˏˋ⋆ 𝐆𝐢𝐟𝐭 𝐒𝐤𝐢𝐧 ⋆ˊˎ-\n\n★ 𝑩𝒂𝒔𝒊𝒄\n 💎 𝟸𝟼𝟿 : 𝟹𝟾.𝟻𝟶𝟶\n 💎 𝟸𝟿𝟿 : 𝟺𝟹.𝟶𝟶𝟶\n★ 𝑬𝒍𝒊𝒕𝒆\n 💎 𝟹𝟿𝟿 : 𝟻𝟺.𝟶𝟶𝟶\n 💎 𝟻𝟿𝟿 : 𝟾𝟶.𝟶𝟶𝟶\n★ 𝑺𝒑𝒆𝒄𝒊𝒂𝒍\n 💎 𝟽𝟺𝟿 : 𝟿𝟿.𝟶𝟶𝟶\n★ 𝑬𝒑𝒊𝒄\n 💎 𝟾𝟿𝟿 : 𝟷𝟷𝟿.𝟶𝟶𝟶\n★ 𝑳𝒊𝒈𝒉𝒕𝒃𝒐𝒓𝒏\n 💎 𝟷.𝟶𝟾𝟿 : 𝟷𝟺𝟸.𝟶𝟶𝟶\n\n𖧷. ᴄɴ/ᴜɴғᴏʟ = ʜᴀɴɢᴜs\n𖧷. ɴᴏ ɢᴀɴᴛɪ ɴɪᴄᴋɴᴀᴍᴇ\n𖧷. ᴅɪᴋɪʀɪᴍ 𝟽-𝟾 ʜᴀʀɪ sᴇᴛᴇʟᴀʜ ʙᴇʀᴛᴇᴍᴀɴ\n𖧷. ᴅɪᴋɪʀɪᴍ sᴇsᴜᴀɪ ᴀɴᴛʀɪᴀɴ\n\n‿︵‿︵୨˚̣̣̣͙୧ - -୨˚̣̣̣͙୧‿︵‿︵",
    "isImage": false,
    "image_url": "-"
  },
  {
    "id": "6287891540792-1601469859@g.us",
    "key": "Tabel Hemat JJK",
    "response": "Tabel Hemat JJK",
    "isImage": true,
    "image_url": "https://telegra.ph/file/84a44c2aff5158345f592.jpg"
  },
  {
    "id": "6287891540792-1601469859@g.us",
    "key": "Format Joki",
    "response": "✮ 𝐅𝐨𝐫𝐦𝐚𝐭 𝐎𝐫𝐝𝐞𝐫 𝐉𝐨𝐤𝐢 ✮\n\n༻❁༺ ─── ⋆⋅☆⋅⋆ ── ༻❁༺\nᥣⱺ𝗀 :\n𝖾ꭑα𝗂ᥣ :\nρα𝗌𝗌ωⱺ𝗋ᑯ :\n𝖼α𝗍α𝗍α𐓣 : \n\n✧ 𝗍іძᥲk ᑲ᥆ᥣᥱһ ᥣ᥆gіᥒ sᥲᥲ𝗍 ⍴ᥱᥒgᥱrȷᥲᥲᥒ\n✧mᥲ𝗍іkᥲᥒ ᥎2ᥣ\n✧⍴ᥲs𝗍іkᥲᥒ ᥱmᥲіᥣ/⍴ᥕ ᑲᥱᥒᥲr\n༻❁༺ ─── ⋆⋅☆⋅⋆ ── ༻❁༺",
    "isImage": false,
    "image_url": "-"
  }
]
